{
  "title": "Example: Add workspace health badge to README",
  "description": "This is a demonstration proposal showing the Enhancement Bot's JSON format. It serves as a template for future proposals. The associated script is a no-op that logs its execution. In a real proposal, the script would perform an actual improvement like fixing typos, updating documentation, or cleaning up stale files.",
  "priority": 5,
  "script": "scripts/example-noop.sh",
  "status": "proposed",
  "created_at": "2026-02-26T17:00:00Z",
  "updated_at": "2026-02-26T17:00:00Z",
  "implemented_at": null,
  "failed_at": null,
  "result": ""
}